yesnopy/__init__.py
yesnopy/yesnopy.py
yesnopy-0.0.3.dist-info/LICENSE
yesnopy-0.0.3.dist-info/METADATA
yesnopy-0.0.3.dist-info/WHEEL
yesnopy-0.0.3.dist-info/top_level.txt
yesnopy-0.0.3.dist-info/RECORD
