Metadata-Version: 2.1
Name: yesnopy
Version: 0.0.3
Summary: Save time by automatically checking user decision input
Author-email: Arnav Nagpure <arnav.n256@gmail.com>
Project-URL: Homepage, https://github.com/AN1001/yesnopy
Project-URL: Bug Tracker, https://github.com/AN1001/yesnopy/issues
Classifier: Programming Language :: Python :: 3
Classifier: License :: OSI Approved :: MIT License
Classifier: Operating System :: OS Independent
Requires-Python: >=3.5.0
License-File: LICENSE
